Workbook

Sheet Параметры
A1: Параметры модели — меняем синие ячейки на жёлтом
A3: Параметр | B3: Значение | C3: Ед. | D3: Комментарий
A4: Фиксированные затраты (лизинг + страховка) | B4: 2000 | C4: руб/сут | D4: дано
A5: Переменные затраты на пробег | B5: 15 | C5: руб/км | D5: дано
A6: Утилизация минутной базы (эконом, доля времени под заказом) | B6: 0.18 | C6: доля | D6: 📊 Москва: эконом ~94-110 км/сут / эфф.скорость -> util ~16-21%; задача даёт 30% по парку, но это среднее, завышенное пакетами
A7: Целевая GP-маржа | B7: 0.3 | C7: доля | D7: цель по gross profit
A8: Эффективная скорость (дистанция/длительность поездки) | B8: 24 | C8: км/ч | D8: 📊 Москва: ср.поездка 23 км/63 мин = 22; Делимобиль 24-27. Эффективная (со стоянками внутри) — НЕ скорость в движении
A9: Плата за км в пакетах | B9: 18 | C9: руб/км | D9: выше предельных издержек по условию Шмалензее (R6: предельный участник легче среднего); коридор [15;21]
A10: Поездок на машину в сутки | B10: 10 | C10: шт/сут | D10: ≈ 432 мин под заказом / ~40 мин на поездку
A11: Ходовая доля (R4): доля времени аренды в движении | B11: 0.55 | C11: доля | D11: справочно (Sprei): в эффективную скорость B8 уже заложена; для предельного пола НЕ используется — иначе двойной учёт
A12: Теневая цена ёмкости в пик (R5) | B12: 0 | C12: руб/мин | D12: R5: off-peak ≈ 0; в пик растёт и поднимает предельный пол (peak-load)
A13: Утилизация по длительности аренды (доля времени под заказом)
A14: Тариф | B14: Утилизация | D14: ВАЖНО: замените на реальную утилизацию по длительностям из вашей статистики
A15: 1 час | B15: 0.4
A16: 2 часа | B16: 0.45
A17: 3 часа | B17: 0.5
A18: 6 часов | B18: 0.55
A19: 12 часов | B19: 0.7
A20: 1 сутки | B20: 0.85
A21: 7 суток | B21: 0.95

Sheet Юнит-экономика
A1: Юнит-экономика средней машины (база = минутный тариф)
A3: Часов под заказом в сутки | B3: =24*Параметры!B6 | C3: ч
A4: Минут под заказом в сутки | B4: =B3*60 | C4: мин
A5: Пробег в сутки | B5: =B3*Параметры!B8 | C5: км
A7: Фиксированные затраты / сут | B7: =Параметры!B4 | C7: руб
A8: Переменные затраты / сут | B8: =B5*Параметры!B5 | C8: руб
A9: Итого затраты / сут | B9: =B7+B8 | C9: руб
A11: Выручка для целевой маржи | B11: =B9/(1-Параметры!B7) | C11: руб
A12: Gross Profit / сут | B12: =B11-B9 | C12: руб
A13: Факт. GP-маржа (проверка) | B13: =B12/B11 | C13: %
A15: Минутный тариф
A16: Ставка, руб/мин | B16: =B11/B4 | C16: руб/мин
A17: — фикс. компонента (покрывает простой) | B17: =B7/B4 | C17: руб/мин
A18: — перем. компонента (себест. за минуты движения) | B18: =(Параметры!B8/60)*Параметры!B5 | C18: руб/мин
A19: — себестоимость, руб/мин | B19: =B17+B18 | C19: руб/мин
A20: — с маржой /(1-маржа), сверка с B16 | B20: =B19/(1-Параметры!B7) | C20: руб/мин
A22: Предельный пол vs средний таргет (R5)
A23: Средний таргет безубыточности (FDC + маржа) = ставка B16 | B23: =B16 | C23: руб/мин
A24: Предельный пол — вариативная компонента, ₽ за минуту аренды | B24: =B18 | C24: руб/мин
A25: Предельный пол, off-peak — на забронированную минуту (B8 эффективная -> без ×ходовая доля) | B25: =B18 | C25: руб/мин
A26: Предельный пол, peak (+ теневая цена ёмкости) | B26: =B25+Параметры!B12 | C26: руб/мин
A27: Рыночный ориентир эконом-минуты (📊 Москва ~8.5) | B27: 8.5 | C27: руб/мин
A28: Данные Москвы: пол ~6 < рынок ~8.5 ≪ таргет ~20. Рынок впритык над полом, далеко под таргетом — фикс отбивается не минутной ставкой
A29: Пол = операционные предельные + теневая цена ёмкости (статически peak-load, динамически Беллман)

Sheet Тарифы
A1: Тарифная сетка: фикс-ставка за час падает с длительностью — это и есть «пакет дешевле»
A3: Тариф | B3: Утилизация | C3: Фикс-затрата на час под заказом, руб | D3: Фикс-плата за час (с маржой), руб/ч | E3: Часов в аренде | F3: Фикс-плата за весь пакет, руб | G3: Плата за км, руб | H3: Себест. за км, руб | I3: Пример: пакет + 30 км, руб
A4: Минутный (справочно) | B4: =Параметры!B6 | C4: =Параметры!B4/(24*B4) | D4: =C4/(1-Параметры!B7) | E4: — | F4: — | G4: =(Параметры!B8/60)*Параметры!B5/(1-Параметры!B7) | H4: =Параметры!B5 | I4: —
A5: 1 час | B5: =Параметры!B15 | C5: =Параметры!B4/(24*B5) | D5: =C5/(1-Параметры!B7) | E5: 1 | F5: =D5*E5 | G5: =Параметры!B9 | H5: =Параметры!B5 | I5: =F5+G5*30
A6: 2 часа | B6: =Параметры!B16 | C6: =Параметры!B4/(24*B6) | D6: =C6/(1-Параметры!B7) | E6: 2 | F6: =D6*E6 | G6: =Параметры!B9 | H6: =Параметры!B5 | I6: =F6+G6*30
A7: 3 часа | B7: =Параметры!B17 | C7: =Параметры!B4/(24*B7) | D7: =C7/(1-Параметры!B7) | E7: 3 | F7: =D7*E7 | G7: =Параметры!B9 | H7: =Параметры!B5 | I7: =F7+G7*30
A8: 6 часов | B8: =Параметры!B18 | C8: =Параметры!B4/(24*B8) | D8: =C8/(1-Параметры!B7) | E8: 6 | F8: =D8*E8 | G8: =Параметры!B9 | H8: =Параметры!B5 | I8: =F8+G8*30
A9: 12 часов | B9: =Параметры!B19 | C9: =Параметры!B4/(24*B9) | D9: =C9/(1-Параметры!B7) | E9: 12 | F9: =D9*E9 | G9: =Параметры!B9 | H9: =Параметры!B5 | I9: =F9+G9*30
A10: 1 сутки | B10: =Параметры!B20 | C10: =Параметры!B4/(24*B10) | D10: =C10/(1-Параметры!B7) | E10: 24 | F10: =D10*E10 | G10: =Параметры!B9 | H10: =Параметры!B5 | I10: =F10+G10*30
A11: 7 суток | B11: =Параметры!B21 | C11: =Параметры!B4/(24*B11) | D11: =C11/(1-Параметры!B7) | E11: 168 | F11: =D11*E11 | G11: =Параметры!B9 | H11: =Параметры!B5 | I11: =F11+G11*30
A14: Фиксированный тариф А→Б (на примере одной поездки)
A15: Прогноз пробега | B15: 10 | C15: км
A16: Прогноз длительности | B16: 24 | C16: мин
A17: Себестоимость поездки | B17: =(Параметры!B4/'Юнит-экономика'!B4)*B16+Параметры!B5*B15 | C17: руб
A18: Цена по себестоимости с маржой | B18: =B17/(1-Параметры!B7) | C18: руб
A19: Коммерческая скидка А→Б (стимул брать фикс) | B19: 0.07 | C19: доля
A20: Итоговая цена А→Б | B20: =B18*(1-B19) | C20: руб
A21: Та же поездка минутным тарифом | B21: =B16*'Юнит-экономика'!B16 | C21: руб
A22: Выгода клиента к минутному | B22: =1-B20/B21 | C22: %

Sheet Сервисный_сбор
A1: Сервисный сбор: фикс. плата за поездку поверх тарифа
A3: Базовая выручка / сут (без сбора) | B3: ='Юнит-экономика'!B11
A4: Затраты / сут | B4: ='Юнит-экономика'!B9
A5: Поездок / сут | B5: =Параметры!B10
A6: Средний чек поездки | B6: =B3/B5
A8: Сценарии размера сбора
A9: Сбор за поездку, руб | B9: 30 | C9: 50 | D9: 80
A10: Доп. выручка / сут | B10: =$B$5*B9 | C10: =$B$5*C9 | D10: =$B$5*D9
A11: Новая выручка / сут (ставки прежние) | B11: =$B$3+B10 | C11: =$B$3+C10 | D11: =$B$3+D10
A12: Новая GP-маржа | B12: =($B$3+B10-$B$4)/($B$3+B10) | C12: =($B$3+C10-$B$4)/($B$3+C10) | D12: =($B$3+D10-$B$4)/($B$3+D10)
A13: Сбор как % среднего чека | B13: =B9/$B$6 | C13: =C9/$B$6 | D13: =D9/$B$6
A15: Альтернатива: держим маржу 30%, снижаем минутную ставку
A16: Целевая общая выручка (= затраты / (1-маржа)) | B16: =$B$4/(1-Параметры!B7)
A17: Нужная выручка с тарифа (минус сбор) | B17: =$B$16-B10 | C17: =$B$16-C10 | D17: =$B$16-D10
A18: Новая минутная ставка, руб/мин | B18: =B17/'Юнит-экономика'!B4 | C18: =C17/'Юнит-экономика'!B4 | D18: =D17/'Юнит-экономика'!B4
A19: Базовая минутная ставка (для сравнения) | B19: ='Юнит-экономика'!B16
A21: На что влияет сбор:
A22: • сильнее всего бьёт по коротким поездкам (сбор = большая доля чека) → может срезать частые короткие сценарии
A23: • двигает выручку из заметной минутной ставки в незаметный фикс → можно показывать ставку ниже конкурентов
A24: • честно собирает фикс. косты на поездку (подача, уборка, поддержка, страховка), не зависящие от км/времени
A25: • риски: падение конверсии в бронь, отток high-frequency юзеров; смягчается порогом/освобождением для подписки
